[{"toc_title":"Microsoft.Azure.Management.AppService.Fluent.AppServiceDomain.Update","href":"../microsoft.azure.management.appservice.fluent.appservicedomain.update","children":[{"toc_title":"IUpdate","href":"../microsoft.azure.management.appservice.fluent.appservicedomain.update.iupdate","version":["azuremgmtappservice-fluent-1.0.0"]},{"toc_title":"IWithAdminContact","href":"../microsoft.azure.management.appservice.fluent.appservicedomain.update.iwithadmincontact","children":[{"toc_title":"Methods","children":[{"toc_title":"WithAdminContact","href":"../microsoft.azure.management.appservice.fluent.appservicedomain.update.iwithadmincontact.withadmincontact","version":["azuremgmtappservice-fluent-1.0.0"]}]}],"version":["azuremgmtappservice-fluent-1.0.0"]},{"toc_title":"IWithAutoRenew","href":"../microsoft.azure.management.appservice.fluent.appservicedomain.update.iwithautorenew","children":[{"toc_title":"Methods","children":[{"toc_title":"WithAutoRenewEnabled","href":"../microsoft.azure.management.appservice.fluent.appservicedomain.update.iwithautorenew.withautorenewenabled","version":["azuremgmtappservice-fluent-1.0.0"]}]}],"version":["azuremgmtappservice-fluent-1.0.0"]},{"toc_title":"IWithBillingContact","href":"../microsoft.azure.management.appservice.fluent.appservicedomain.update.iwithbillingcontact","children":[{"toc_title":"Methods","children":[{"toc_title":"WithBillingContact","href":"../microsoft.azure.management.appservice.fluent.appservicedomain.update.iwithbillingcontact.withbillingcontact","version":["azuremgmtappservice-fluent-1.0.0"]}]}],"version":["azuremgmtappservice-fluent-1.0.0"]},{"toc_title":"IWithDomainPrivacy","href":"../microsoft.azure.management.appservice.fluent.appservicedomain.update.iwithdomainprivacy","children":[{"toc_title":"Methods","children":[{"toc_title":"WithDomainPrivacyEnabled","href":"../microsoft.azure.management.appservice.fluent.appservicedomain.update.iwithdomainprivacy.withdomainprivacyenabled","version":["azuremgmtappservice-fluent-1.0.0"]}]}],"version":["azuremgmtappservice-fluent-1.0.0"]},{"toc_title":"IWithTechContact","href":"../microsoft.azure.management.appservice.fluent.appservicedomain.update.iwithtechcontact","children":[{"toc_title":"Methods","children":[{"toc_title":"WithTechContact","href":"../microsoft.azure.management.appservice.fluent.appservicedomain.update.iwithtechcontact.withtechcontact","version":["azuremgmtappservice-fluent-1.0.0"]}]}],"version":["azuremgmtappservice-fluent-1.0.0"]}],"version":["azuremgmtappservice-fluent-1.0.0"],"pdf_name":"/Microsoft.Azure.Management.AppService.Fluent.AppServiceDomain.Update.pdf"}]