[{"toc_title":"Microsoft.Azure.Management.Sql.Fluent.SqlFirewallRule.Definition","href":"../microsoft.azure.management.sql.fluent.sqlfirewallrule.definition","children":[{"toc_title":"IBlank","href":"../microsoft.azure.management.sql.fluent.sqlfirewallrule.definition.iblank","version":["azuremgmtsql-fluent-1.0.0"]},{"toc_title":"IDefinition","href":"../microsoft.azure.management.sql.fluent.sqlfirewallrule.definition.idefinition","version":["azuremgmtsql-fluent-1.0.0"]},{"toc_title":"IWithCreate","href":"../microsoft.azure.management.sql.fluent.sqlfirewallrule.definition.iwithcreate","version":["azuremgmtsql-fluent-1.0.0"]},{"toc_title":"IWithIPAddress","href":"../microsoft.azure.management.sql.fluent.sqlfirewallrule.definition.iwithipaddress","children":[{"toc_title":"Methods","children":[{"toc_title":"WithIPAddress","href":"../microsoft.azure.management.sql.fluent.sqlfirewallrule.definition.iwithipaddress.withipaddress","version":["azuremgmtsql-fluent-1.0.0"]}]}],"version":["azuremgmtsql-fluent-1.0.0"]},{"toc_title":"IWithIPAddressRange","href":"../microsoft.azure.management.sql.fluent.sqlfirewallrule.definition.iwithipaddressrange","children":[{"toc_title":"Methods","children":[{"toc_title":"WithIPAddressRange","href":"../microsoft.azure.management.sql.fluent.sqlfirewallrule.definition.iwithipaddressrange.withipaddressrange","version":["azuremgmtsql-fluent-1.0.0"]}]}],"version":["azuremgmtsql-fluent-1.0.0"]}],"version":["azuremgmtsql-fluent-1.0.0"],"pdf_name":"/Microsoft.Azure.Management.Sql.Fluent.SqlFirewallRule.Definition.pdf"}]