{"author":"dotnet-bot","ms.author":"dotnetcontent","manager":"wpickett","breadcrumb_path":"/dotnet/toc.json","apiPlatform":"dotnet","ms.topic":"managed-reference","ms.prod":".net","search.ms_sitename":"Docs","search.ms_docsetname":"docs-internal","version":0,"locale":"en-us","site_name":"Docs","search.ms_product":"MSDN","depot_name":"MSDN.docs-internal","original_ref_skeleton_git_url":"https://github.com/dotnet/docs-internal/blob/master/api/System.ServiceModel.Description.WebScriptEnablingBehavior.yml","open_to_public_contributors":false,"api_name":["System.ServiceModel.Description.WebScriptEnablingBehavior","System.ServiceModel.Description.WebScriptEnablingBehavior..ctor","System.ServiceModel.Description.WebScriptEnablingBehavior.AddClientErrorInspector","System.ServiceModel.Description.WebScriptEnablingBehavior.AddServerErrorHandlers","System.ServiceModel.Description.WebScriptEnablingBehavior.ApplyClientBehavior","System.ServiceModel.Description.WebScriptEnablingBehavior.ApplyDispatchBehavior","System.ServiceModel.Description.WebScriptEnablingBehavior.AutomaticFormatSelectionEnabled","System.ServiceModel.Description.WebScriptEnablingBehavior.DefaultBodyStyle","System.ServiceModel.Description.WebScriptEnablingBehavior.DefaultOutgoingRequestFormat","System.ServiceModel.Description.WebScriptEnablingBehavior.DefaultOutgoingResponseFormat","System.ServiceModel.Description.WebScriptEnablingBehavior.FaultExceptionEnabled","System.ServiceModel.Description.WebScriptEnablingBehavior.GetQueryStringConverter","System.ServiceModel.Description.WebScriptEnablingBehavior.HelpEnabled","System.ServiceModel.Description.WebScriptEnablingBehavior.Validate"],"api_location":["System.ServiceModel.Web.dll"],"topic_type":["apiref"],"api_type":["Assembly"],"f1_keywords":["System.ServiceModel.Description.WebScriptEnablingBehavior","System::ServiceModel::Description::WebScriptEnablingBehavior","System.ServiceModel.Description.WebScriptEnablingBehavior.#ctor","System::ServiceModel::Description::WebScriptEnablingBehavior::#ctor","System.ServiceModel.Description.WebScriptEnablingBehavior.AddClientErrorInspector","System::ServiceModel::Description::WebScriptEnablingBehavior::AddClientErrorInspector","System.ServiceModel.Description.WebScriptEnablingBehavior.AddServerErrorHandlers","System::ServiceModel::Description::WebScriptEnablingBehavior::AddServerErrorHandlers","System.ServiceModel.Description.WebScriptEnablingBehavior.ApplyClientBehavior","System::ServiceModel::Description::WebScriptEnablingBehavior::ApplyClientBehavior","System.ServiceModel.Description.WebScriptEnablingBehavior.ApplyDispatchBehavior","System::ServiceModel::Description::WebScriptEnablingBehavior::ApplyDispatchBehavior","System.ServiceModel.Description.WebScriptEnablingBehavior.AutomaticFormatSelectionEnabled","System::ServiceModel::Description::WebScriptEnablingBehavior::AutomaticFormatSelectionEnabled","System.ServiceModel.Description.WebScriptEnablingBehavior.DefaultBodyStyle","System::ServiceModel::Description::WebScriptEnablingBehavior::DefaultBodyStyle","System.ServiceModel.Description.WebScriptEnablingBehavior.DefaultOutgoingRequestFormat","System::ServiceModel::Description::WebScriptEnablingBehavior::DefaultOutgoingRequestFormat","System.ServiceModel.Description.WebScriptEnablingBehavior.DefaultOutgoingResponseFormat","System::ServiceModel::Description::WebScriptEnablingBehavior::DefaultOutgoingResponseFormat","System.ServiceModel.Description.WebScriptEnablingBehavior.FaultExceptionEnabled","System::ServiceModel::Description::WebScriptEnablingBehavior::FaultExceptionEnabled","System.ServiceModel.Description.WebScriptEnablingBehavior.GetQueryStringConverter","System::ServiceModel::Description::WebScriptEnablingBehavior::GetQueryStringConverter","System.ServiceModel.Description.WebScriptEnablingBehavior.HelpEnabled","System::ServiceModel::Description::WebScriptEnablingBehavior::HelpEnabled","System.ServiceModel.Description.WebScriptEnablingBehavior.Validate","System::ServiceModel::Description::WebScriptEnablingBehavior::Validate"],"dev_langs":["csharp"],"updated_at":"2017-03-31 02:21 PM","document_id":"1bfaa2a5-be15-5633-f923-a1396aeac522","content_git_url":"https://github.com/dotnet/docs-internal/blob/master/xml/System.ServiceModel.Description/WebScriptEnablingBehavior.xml","layout":"Reference","pagetype":"Reference","title":"WebScriptEnablingBehavior class | Microsoft Docs","description":"Provides support for the behavior that enables Windows Communication Foundation (WCF) endpoints to receive HTTP requests from a browser-based ASP.NET AJAX client. This class cannot be inherited.\n","toc_asset_id":"api/_splitted/System.ServiceModel.Description/toc.json","toc_rel":"_splitted/System.ServiceModel.Description/toc.json","source_url":"","ms.assetid":"System.ServiceModel.Description.WebScriptEnablingBehavior","canonical_url":"https://ppe.docs.microsoft.com/en-us/dotnet/api/system.servicemodel.description.webscriptenablingbehavior","is_dynamic_rendering":true,"content_type":"application/json","publish_version":"{\"opbuild.templates.docs\":\"1.30.5\",\"commit_id\":\"17a3ab678719a445c946d4cd72cab2ee5e79df28\",\"branch\":\"master\",\"opbuild.scripts\":\"1.30.5\",\"opbuild.htmltopdftool\":\"1.30.5\",\"opbuild.gitcontributorinformationresolver\":\"1.30.5\",\"opbuild_service\":\"1.30.130.0\",\"docfx.console\":\"2.15.3\",\"opbuild.resolvedependencyconsole\":\"1.30.5\",\"opbuild.schemavalidationconsole\":\"1.30.5\",\"opbuild.redirectionresolver\":\"1.30.5\",\"opbuild.templates.intellisense\":\"1.30.5\",\"dependencies\":[{\"branch\":\"preview\",\"path\":\"_themes\",\"url\":\"https://github.com/Microsoft/templates.docs.msft\",\"commit_id\":\"8daeea589e77ebbd2ac22b9cd5a9d8bf8e69aed2\",\"opbuild.templates.common\":\"1.30.5\"},{\"branch\":\"master\",\"path\":\"_themes.pdf\",\"url\":\"https://github.com/Microsoft/templates.docs.msft.pdf\",\"commit_id\":\"ed2aa9642124365e156c2670dab210e368095ebd\",\"opbuild.templates.common\":\"1.30.5\"}]}"}