{"author":"dotnet-bot","ms.author":"dotnetcontent","manager":"wpickett","breadcrumb_path":"/dotnet/toc.json","ms.topic":"managed-reference","ms.prod":".net","search.ms_sitename":"Docs","search.ms_docsetname":"docs-internal","version":0,"locale":"en-us","site_name":"Docs","search.ms_product":"MSDN","depot_name":"MSDN.docs-internal","original_ref_skeleton_git_url":"https://github.com/dotnet/docs-internal/blob/master/api/System.Windows.Forms.UpDownBase.yml","open_to_public_contributors":false,"api_name":["System.Windows.Forms.UpDownBase","System.Windows.Forms.UpDownBase..ctor","System.Windows.Forms.UpDownBase.AutoScroll","System.Windows.Forms.UpDownBase.AutoScrollMargin","System.Windows.Forms.UpDownBase.AutoScrollMinSize","System.Windows.Forms.UpDownBase.AutoSize","System.Windows.Forms.UpDownBase.AutoSizeChanged","System.Windows.Forms.UpDownBase.add_AutoSizeChanged","System.Windows.Forms.UpDownBase.remove_AutoSizeChanged","System.Windows.Forms.UpDownBase.BackColor","System.Windows.Forms.UpDownBase.BackgroundImage","System.Windows.Forms.UpDownBase.BackgroundImageChanged","System.Windows.Forms.UpDownBase.add_BackgroundImageChanged","System.Windows.Forms.UpDownBase.remove_BackgroundImageChanged","System.Windows.Forms.UpDownBase.BackgroundImageLayout","System.Windows.Forms.UpDownBase.BackgroundImageLayoutChanged","System.Windows.Forms.UpDownBase.add_BackgroundImageLayoutChanged","System.Windows.Forms.UpDownBase.remove_BackgroundImageLayoutChanged","System.Windows.Forms.UpDownBase.BorderStyle","System.Windows.Forms.UpDownBase.ChangingText","System.Windows.Forms.UpDownBase.ContextMenu","System.Windows.Forms.UpDownBase.ContextMenuStrip","System.Windows.Forms.UpDownBase.CreateParams","System.Windows.Forms.UpDownBase.DefaultSize","System.Windows.Forms.UpDownBase.DockPadding","System.Windows.Forms.UpDownBase.DownButton","System.Windows.Forms.UpDownBase.Focused","System.Windows.Forms.UpDownBase.ForeColor","System.Windows.Forms.UpDownBase.InterceptArrowKeys","System.Windows.Forms.UpDownBase.MaximumSize","System.Windows.Forms.UpDownBase.MinimumSize","System.Windows.Forms.UpDownBase.MouseEnter","System.Windows.Forms.UpDownBase.add_MouseEnter","System.Windows.Forms.UpDownBase.remove_MouseEnter","System.Windows.Forms.UpDownBase.MouseHover","System.Windows.Forms.UpDownBase.add_MouseHover","System.Windows.Forms.UpDownBase.remove_MouseHover","System.Windows.Forms.UpDownBase.MouseLeave","System.Windows.Forms.UpDownBase.add_MouseLeave","System.Windows.Forms.UpDownBase.remove_MouseLeave","System.Windows.Forms.UpDownBase.MouseMove","System.Windows.Forms.UpDownBase.add_MouseMove","System.Windows.Forms.UpDownBase.remove_MouseMove","System.Windows.Forms.UpDownBase.OnChanged","System.Windows.Forms.UpDownBase.OnFontChanged","System.Windows.Forms.UpDownBase.OnHandleCreated","System.Windows.Forms.UpDownBase.OnHandleDestroyed","System.Windows.Forms.UpDownBase.OnLayout","System.Windows.Forms.UpDownBase.OnMouseDown","System.Windows.Forms.UpDownBase.OnMouseUp","System.Windows.Forms.UpDownBase.OnMouseWheel","System.Windows.Forms.UpDownBase.OnPaint","System.Windows.Forms.UpDownBase.OnTextBoxKeyDown","System.Windows.Forms.UpDownBase.OnTextBoxKeyPress","System.Windows.Forms.UpDownBase.OnTextBoxLostFocus","System.Windows.Forms.UpDownBase.OnTextBoxResize","System.Windows.Forms.UpDownBase.OnTextBoxTextChanged","System.Windows.Forms.UpDownBase.PreferredHeight","System.Windows.Forms.UpDownBase.ReadOnly","System.Windows.Forms.UpDownBase.Select","System.Windows.Forms.UpDownBase.Text","System.Windows.Forms.UpDownBase.TextAlign","System.Windows.Forms.UpDownBase.UpButton","System.Windows.Forms.UpDownBase.UpdateEditText","System.Windows.Forms.UpDownBase.UpDownAlign","System.Windows.Forms.UpDownBase.UserEdit","System.Windows.Forms.UpDownBase.ValidateEditText","System.Windows.Forms.UpDownBase.WndProc"],"api_location":["System.Windows.Forms.dll"],"topic_type":["apiref"],"api_type":["Assembly"],"f1_keywords":["System.Windows.Forms.UpDownBase","System::Windows::Forms::UpDownBase","System.Windows.Forms.UpDownBase.#ctor","System::Windows::Forms::UpDownBase::#ctor","System.Windows.Forms.UpDownBase.AutoScroll","System::Windows::Forms::UpDownBase::AutoScroll","System.Windows.Forms.UpDownBase.AutoScrollMargin","System::Windows::Forms::UpDownBase::AutoScrollMargin","System.Windows.Forms.UpDownBase.AutoScrollMinSize","System::Windows::Forms::UpDownBase::AutoScrollMinSize","System.Windows.Forms.UpDownBase.AutoSize","System::Windows::Forms::UpDownBase::AutoSize","System.Windows.Forms.UpDownBase.AutoSizeChanged","System::Windows::Forms::UpDownBase::AutoSizeChanged","System.Windows.Forms.UpDownBase.BackColor","System::Windows::Forms::UpDownBase::BackColor","System.Windows.Forms.UpDownBase.BackgroundImage","System::Windows::Forms::UpDownBase::BackgroundImage","System.Windows.Forms.UpDownBase.BackgroundImageChanged","System::Windows::Forms::UpDownBase::BackgroundImageChanged","System.Windows.Forms.UpDownBase.BackgroundImageLayout","System::Windows::Forms::UpDownBase::BackgroundImageLayout","System.Windows.Forms.UpDownBase.BackgroundImageLayoutChanged","System::Windows::Forms::UpDownBase::BackgroundImageLayoutChanged","System.Windows.Forms.UpDownBase.BorderStyle","System::Windows::Forms::UpDownBase::BorderStyle","System.Windows.Forms.UpDownBase.ChangingText","System::Windows::Forms::UpDownBase::ChangingText","System.Windows.Forms.UpDownBase.ContextMenu","System::Windows::Forms::UpDownBase::ContextMenu","System.Windows.Forms.UpDownBase.ContextMenuStrip","System::Windows::Forms::UpDownBase::ContextMenuStrip","System.Windows.Forms.UpDownBase.CreateParams","System::Windows::Forms::UpDownBase::CreateParams","System.Windows.Forms.UpDownBase.DefaultSize","System::Windows::Forms::UpDownBase::DefaultSize","System.Windows.Forms.UpDownBase.DockPadding","System::Windows::Forms::UpDownBase::DockPadding","System.Windows.Forms.UpDownBase.DownButton","System::Windows::Forms::UpDownBase::DownButton","System.Windows.Forms.UpDownBase.Focused","System::Windows::Forms::UpDownBase::Focused","System.Windows.Forms.UpDownBase.ForeColor","System::Windows::Forms::UpDownBase::ForeColor","System.Windows.Forms.UpDownBase.InterceptArrowKeys","System::Windows::Forms::UpDownBase::InterceptArrowKeys","System.Windows.Forms.UpDownBase.MaximumSize","System::Windows::Forms::UpDownBase::MaximumSize","System.Windows.Forms.UpDownBase.MinimumSize","System::Windows::Forms::UpDownBase::MinimumSize","System.Windows.Forms.UpDownBase.MouseEnter","System::Windows::Forms::UpDownBase::MouseEnter","System.Windows.Forms.UpDownBase.MouseHover","System::Windows::Forms::UpDownBase::MouseHover","System.Windows.Forms.UpDownBase.MouseLeave","System::Windows::Forms::UpDownBase::MouseLeave","System.Windows.Forms.UpDownBase.MouseMove","System::Windows::Forms::UpDownBase::MouseMove","System.Windows.Forms.UpDownBase.OnChanged","System::Windows::Forms::UpDownBase::OnChanged","System.Windows.Forms.UpDownBase.OnFontChanged","System::Windows::Forms::UpDownBase::OnFontChanged","System.Windows.Forms.UpDownBase.OnHandleCreated","System::Windows::Forms::UpDownBase::OnHandleCreated","System.Windows.Forms.UpDownBase.OnHandleDestroyed","System::Windows::Forms::UpDownBase::OnHandleDestroyed","System.Windows.Forms.UpDownBase.OnLayout","System::Windows::Forms::UpDownBase::OnLayout","System.Windows.Forms.UpDownBase.OnMouseDown","System::Windows::Forms::UpDownBase::OnMouseDown","System.Windows.Forms.UpDownBase.OnMouseUp","System::Windows::Forms::UpDownBase::OnMouseUp","System.Windows.Forms.UpDownBase.OnMouseWheel","System::Windows::Forms::UpDownBase::OnMouseWheel","System.Windows.Forms.UpDownBase.OnPaint","System::Windows::Forms::UpDownBase::OnPaint","System.Windows.Forms.UpDownBase.OnTextBoxKeyDown","System::Windows::Forms::UpDownBase::OnTextBoxKeyDown","System.Windows.Forms.UpDownBase.OnTextBoxKeyPress","System::Windows::Forms::UpDownBase::OnTextBoxKeyPress","System.Windows.Forms.UpDownBase.OnTextBoxLostFocus","System::Windows::Forms::UpDownBase::OnTextBoxLostFocus","System.Windows.Forms.UpDownBase.OnTextBoxResize","System::Windows::Forms::UpDownBase::OnTextBoxResize","System.Windows.Forms.UpDownBase.OnTextBoxTextChanged","System::Windows::Forms::UpDownBase::OnTextBoxTextChanged","System.Windows.Forms.UpDownBase.PreferredHeight","System::Windows::Forms::UpDownBase::PreferredHeight","System.Windows.Forms.UpDownBase.ReadOnly","System::Windows::Forms::UpDownBase::ReadOnly","System.Windows.Forms.UpDownBase.Select","System::Windows::Forms::UpDownBase::Select","System.Windows.Forms.UpDownBase.Text","System::Windows::Forms::UpDownBase::Text","System.Windows.Forms.UpDownBase.TextAlign","System::Windows::Forms::UpDownBase::TextAlign","System.Windows.Forms.UpDownBase.UpButton","System::Windows::Forms::UpDownBase::UpButton","System.Windows.Forms.UpDownBase.UpdateEditText","System::Windows::Forms::UpDownBase::UpdateEditText","System.Windows.Forms.UpDownBase.UpDownAlign","System::Windows::Forms::UpDownBase::UpDownAlign","System.Windows.Forms.UpDownBase.UserEdit","System::Windows::Forms::UpDownBase::UserEdit","System.Windows.Forms.UpDownBase.ValidateEditText","System::Windows::Forms::UpDownBase::ValidateEditText","System.Windows.Forms.UpDownBase.WndProc","System::Windows::Forms::UpDownBase::WndProc"],"dev_langs":["csharp"],"updated_at":"2017-03-23 08:04 AM","document_id":"f43cfa53-ec24-ae2e-1161-841d3d466326","content_git_url":"https://github.com/dotnet/docs/blob/master/xml/System.Windows.Forms/UpDownBase.xml","layout":"Reference","pagetype":"Reference","title":"UpDownBase class | Microsoft Docs","description":"Implements the basic functionality required by a spin box (also known as an up-down control).\n","toc_asset_id":"api/_splitted/System.Windows.Forms/toc.json","toc_rel":"_splitted/System.Windows.Forms/toc.json","source_url":"","ms.assetid":"System.Windows.Forms.UpDownBase","canonical_url":"https://ppe.docs.microsoft.com/en-us/dotnet/api/system.windows.forms.updownbase","is_dynamic_rendering":true,"content_type":"application/json","publish_version":"{\"opbuild.templates.docs\":\"1.29.3\",\"commit_id\":\"b3a23883507f33cbc5269a49bae8b286e3a2a4b9\",\"branch\":\"master\",\"opbuild.scripts\":\"1.29.3\",\"opbuild.htmltopdftool\":\"1.29.3\",\"opbuild.gitcontributorinformationresolver\":\"1.29.3\",\"opbuild_service\":\"1.29.125.0\",\"docfx.console\":\"2.14.1\",\"opbuild.resolvedependencyconsole\":\"1.29.3\",\"opbuild.schemavalidationconsole\":\"1.29.3\",\"opbuild.redirectionresolver\":\"1.29.3\",\"opbuild.templates.intellisense\":\"1.29.3\",\"dependencies\":[{\"branch\":\"preview\",\"path\":\"_themes\",\"url\":\"https://github.com/Microsoft/templates.docs.msft\",\"commit_id\":\"eff7969f07a808864b2febe5a48618a2674e22af\",\"opbuild.templates.common\":\"1.29.3\"},{\"branch\":\"master\",\"path\":\"_themes.pdf\",\"url\":\"https://github.com/Microsoft/templates.docs.msft.pdf\",\"commit_id\":\"b2158fbf2c62f32aff19e6f61397f4caa40b05f7\",\"opbuild.templates.common\":\"1.29.3\"}]}"}