{"author":"dotnet-bot","ms.author":"dotnetcontent","manager":"wpickett","breadcrumb_path":"/dotnet-internal/toc.json","ms.topic":"managed-reference","ms.prod":".net","search.ms_sitename":"Docs","search.ms_docsetname":"docs-internal","version":0,"locale":"en-us","site_name":"Docs","search.ms_product":"MSDN","depot_name":"MSDN.docs-internal","original_ref_skeleton_git_url":"https://github.com/dotnet/docs-internal/blob/master/api/System.Windows.Forms.TabControl.TabPageCollection.yml","open_to_public_contributors":false,"api_name":["System.Windows.Forms.TabControl.TabPageCollection","System.Windows.Forms.TabControl.TabPageCollection.TabControl..ctor","System.Windows.Forms.TabControl.TabPageCollection.Add","System.Windows.Forms.TabControl.TabPageCollection.AddRange","System.Windows.Forms.TabControl.TabPageCollection.Clear","System.Windows.Forms.TabControl.TabPageCollection.Contains","System.Windows.Forms.TabControl.TabPageCollection.ContainsKey","System.Windows.Forms.TabControl.TabPageCollection.Count","System.Windows.Forms.TabControl.TabPageCollection.GetEnumerator","System.Windows.Forms.TabControl.TabPageCollection.IndexOf","System.Windows.Forms.TabControl.TabPageCollection.IndexOfKey","System.Windows.Forms.TabControl.TabPageCollection.Insert","System.Windows.Forms.TabControl.TabPageCollection.IsReadOnly","System.Windows.Forms.TabControl.TabPageCollection.Item","System.Windows.Forms.TabControl.TabPageCollection.Remove","System.Windows.Forms.TabControl.TabPageCollection.RemoveAt","System.Windows.Forms.TabControl.TabPageCollection.RemoveByKey","System.Windows.Forms.TabControl.TabPageCollection.ICollection.CopyTo","System.Windows.Forms.TabControl.TabPageCollection.ICollection.IsSynchronized","System.Windows.Forms.TabControl.TabPageCollection.ICollection.SyncRoot","System.Windows.Forms.TabControl.TabPageCollection.IList.Add","System.Windows.Forms.TabControl.TabPageCollection.IList.Contains","System.Windows.Forms.TabControl.TabPageCollection.IList.IndexOf","System.Windows.Forms.TabControl.TabPageCollection.IList.Insert","System.Windows.Forms.TabControl.TabPageCollection.IList.IsFixedSize","System.Windows.Forms.TabControl.TabPageCollection.IList.Item","System.Windows.Forms.TabControl.TabPageCollection.IList.Remove"],"api_location":["System.Windows.Forms.dll"],"topic_type":["apiref"],"api_type":["Assembly"],"f1_keywords":["System.Windows.Forms.TabControl.TabPageCollection","System::Windows::Forms::TabControl::TabPageCollection","System.Windows.Forms.TabControl.TabPageCollection.#ctor","System::Windows::Forms::TabControl::TabPageCollection::#ctor","System.Windows.Forms.TabControl.TabPageCollection.Add","System::Windows::Forms::TabControl::TabPageCollection::Add","System.Windows.Forms.TabControl.TabPageCollection.AddRange","System::Windows::Forms::TabControl::TabPageCollection::AddRange","System.Windows.Forms.TabControl.TabPageCollection.Clear","System::Windows::Forms::TabControl::TabPageCollection::Clear","System.Windows.Forms.TabControl.TabPageCollection.Contains","System::Windows::Forms::TabControl::TabPageCollection::Contains","System.Windows.Forms.TabControl.TabPageCollection.ContainsKey","System::Windows::Forms::TabControl::TabPageCollection::ContainsKey","System.Windows.Forms.TabControl.TabPageCollection.Count","System::Windows::Forms::TabControl::TabPageCollection::Count","System.Windows.Forms.TabControl.TabPageCollection.GetEnumerator","System::Windows::Forms::TabControl::TabPageCollection::GetEnumerator","System.Windows.Forms.TabControl.TabPageCollection.IndexOf","System::Windows::Forms::TabControl::TabPageCollection::IndexOf","System.Windows.Forms.TabControl.TabPageCollection.IndexOfKey","System::Windows::Forms::TabControl::TabPageCollection::IndexOfKey","System.Windows.Forms.TabControl.TabPageCollection.Insert","System::Windows::Forms::TabControl::TabPageCollection::Insert","System.Windows.Forms.TabControl.TabPageCollection.IsReadOnly","System::Windows::Forms::TabControl::TabPageCollection::IsReadOnly","System.Windows.Forms.TabControl.TabPageCollection.Item","System::Windows::Forms::TabControl::TabPageCollection::Item","System.Windows.Forms.TabControl.TabPageCollection.Remove","System::Windows::Forms::TabControl::TabPageCollection::Remove","System.Windows.Forms.TabControl.TabPageCollection.RemoveAt","System::Windows::Forms::TabControl::TabPageCollection::RemoveAt","System.Windows.Forms.TabControl.TabPageCollection.RemoveByKey","System::Windows::Forms::TabControl::TabPageCollection::RemoveByKey","System.Windows.Forms.TabControl.TabPageCollection.System#Collections#ICollection#CopyTo","System::Windows::Forms::TabControl::TabPageCollection::System#Collections#ICollection#CopyTo","System.Windows.Forms.TabControl.TabPageCollection.System#Collections#ICollection#IsSynchronized","System::Windows::Forms::TabControl::TabPageCollection::System#Collections#ICollection#IsSynchronized","System.Windows.Forms.TabControl.TabPageCollection.System#Collections#ICollection#SyncRoot","System::Windows::Forms::TabControl::TabPageCollection::System#Collections#ICollection#SyncRoot","System.Windows.Forms.TabControl.TabPageCollection.System#Collections#IList#Add","System::Windows::Forms::TabControl::TabPageCollection::System#Collections#IList#Add","System.Windows.Forms.TabControl.TabPageCollection.System#Collections#IList#Contains","System::Windows::Forms::TabControl::TabPageCollection::System#Collections#IList#Contains","System.Windows.Forms.TabControl.TabPageCollection.System#Collections#IList#IndexOf","System::Windows::Forms::TabControl::TabPageCollection::System#Collections#IList#IndexOf","System.Windows.Forms.TabControl.TabPageCollection.System#Collections#IList#Insert","System::Windows::Forms::TabControl::TabPageCollection::System#Collections#IList#Insert","System.Windows.Forms.TabControl.TabPageCollection.System#Collections#IList#IsFixedSize","System::Windows::Forms::TabControl::TabPageCollection::System#Collections#IList#IsFixedSize","System.Windows.Forms.TabControl.TabPageCollection.System#Collections#IList#Item","System::Windows::Forms::TabControl::TabPageCollection::System#Collections#IList#Item","System.Windows.Forms.TabControl.TabPageCollection.System#Collections#IList#Remove","System::Windows::Forms::TabControl::TabPageCollection::System#Collections#IList#Remove"],"dev_langs":["csharp"],"updated_at":"2017-03-22 02:45 AM","document_id":"142ad5b7-7945-ac60-5530-66aea2528a1d","content_git_url":"https://github.com/TianqiZhang/ECMA2YamlTestRepo2/blob/master/xml/System.Windows.Forms/TabControl+TabPageCollection.xml","layout":"Reference","pagetype":"Reference","title":"TabControl.TabPageCollection class | Microsoft Docs","description":"Contains a collection of  objects.\n","toc_asset_id":"api/_splitted/System.Windows.Forms/toc.json","toc_rel":"_splitted/System.Windows.Forms/toc.json","source_url":"","ms.assetid":"System.Windows.Forms.TabControl.TabPageCollection","canonical_url":"https://ppe.docs.microsoft.com/en-us/dotnet-all/api/system.windows.forms.tabcontrol.tabpagecollection","is_dynamic_rendering":true,"content_type":"application/json","publish_version":"{\"opbuild.templates.docs\":\"1.29.1\",\"commit_id\":\"e33e311da693963bae06fbadce95d30abfc18510\",\"branch\":\"master\",\"opbuild.scripts\":\"1.29.1\",\"opbuild.htmltopdftool\":\"1.29.1\",\"opbuild.gitcontributorinformationresolver\":\"1.29.1\",\"opbuild_service\":\"1.29.121.0\",\"docfx.console\":\"2.14.1\",\"opbuild.resolvedependencyconsole\":\"1.29.1\",\"opbuild.schemavalidationconsole\":\"1.29.1\",\"opbuild.redirectionresolver\":\"1.29.1\",\"opbuild.templates.intellisense\":\"1.29.1\",\"dependencies\":[{\"branch\":\"preview\",\"path\":\"_themes\",\"url\":\"https://github.com/Microsoft/templates.docs.msft\",\"commit_id\":\"bd3ce9826a7b70f96ae3e9981c91aa0b12bc12ad\",\"opbuild.templates.common\":\"1.29.1\"},{\"branch\":\"master\",\"path\":\"_themes.pdf\",\"url\":\"https://github.com/Microsoft/templates.docs.msft.pdf\",\"commit_id\":\"b2158fbf2c62f32aff19e6f61397f4caa40b05f7\",\"opbuild.templates.common\":\"1.29.1\"}]}"}