{"author":"dotnet-bot","ms.author":"dotnetcontent","manager":"wpickett","breadcrumb_path":"/dotnet/toc.json","apiPlatform":"dotnet","ms.topic":"managed-reference","ms.prod":".net","uhfHeaderId":"MSDocsHeader-DotNet","search.ms_sitename":"Docs","search.ms_docsetname":"docs-internal","version":0,"locale":"en-us","site_name":"Docs","search.ms_product":"MSDN","depot_name":"MSDN.docs-internal","original_ref_skeleton_git_url":"https://github.com/dotnet/docs-internal/blob/master/api/System.Diagnostics.Stopwatch.yml","open_to_public_contributors":false,"api_name":["System.Diagnostics.Stopwatch","System.Diagnostics.Stopwatch..ctor","System.Diagnostics.Stopwatch.Elapsed","System.Diagnostics.Stopwatch.ElapsedMilliseconds","System.Diagnostics.Stopwatch.ElapsedTicks","System.Diagnostics.Stopwatch.Frequency","System.Diagnostics.Stopwatch.GetTimestamp","System.Diagnostics.Stopwatch.IsHighResolution","System.Diagnostics.Stopwatch.IsRunning","System.Diagnostics.Stopwatch.Reset","System.Diagnostics.Stopwatch.Restart","System.Diagnostics.Stopwatch.Start","System.Diagnostics.Stopwatch.StartNew","System.Diagnostics.Stopwatch.Stop"],"api_location":["System.dll"],"topic_type":["apiref"],"api_type":["Assembly"],"f1_keywords":["System.Diagnostics.Stopwatch","System::Diagnostics::Stopwatch","System.Diagnostics.Stopwatch.#ctor","System::Diagnostics::Stopwatch::#ctor","System.Diagnostics.Stopwatch.Elapsed","System::Diagnostics::Stopwatch::Elapsed","System.Diagnostics.Stopwatch.ElapsedMilliseconds","System::Diagnostics::Stopwatch::ElapsedMilliseconds","System.Diagnostics.Stopwatch.ElapsedTicks","System::Diagnostics::Stopwatch::ElapsedTicks","System.Diagnostics.Stopwatch.Frequency","System::Diagnostics::Stopwatch::Frequency","System.Diagnostics.Stopwatch.GetTimestamp","System::Diagnostics::Stopwatch::GetTimestamp","System.Diagnostics.Stopwatch.IsHighResolution","System::Diagnostics::Stopwatch::IsHighResolution","System.Diagnostics.Stopwatch.IsRunning","System::Diagnostics::Stopwatch::IsRunning","System.Diagnostics.Stopwatch.Reset","System::Diagnostics::Stopwatch::Reset","System.Diagnostics.Stopwatch.Restart","System::Diagnostics::Stopwatch::Restart","System.Diagnostics.Stopwatch.Start","System::Diagnostics::Stopwatch::Start","System.Diagnostics.Stopwatch.StartNew","System::Diagnostics::Stopwatch::StartNew","System.Diagnostics.Stopwatch.Stop","System::Diagnostics::Stopwatch::Stop"],"dev_langs":["csharp"],"updated_at":"2017-04-01 05:59 PM","document_id":"d2980f3d-de6a-d9bd-bcb4-307507abe446","content_git_url":"https://github.com/dotnet/docs-internal/blob/master/xml/System.Diagnostics/Stopwatch.xml","layout":"Reference","pagetype":"Reference","title":"Stopwatch class | Microsoft Docs","description":"Provides a set of methods and properties that you can use to accurately measure elapsed time.  \n To browse the .NET Framework source code for this type, see the Reference Source.\n","toc_asset_id":"api/_splitted/System.Diagnostics/toc.json","toc_rel":"_splitted/System.Diagnostics/toc.json","source_url":"","ms.assetid":"System.Diagnostics.Stopwatch","canonical_url":"https://ppe.docs.microsoft.com/en-us/dotnet/api/system.diagnostics.stopwatch","is_dynamic_rendering":true,"content_type":"application/json","publish_version":"{\"opbuild.templates.docs\":\"1.30.7\",\"commit_id\":\"67d6937d3b842a046444df1fa9fd48f7e7f0a51c\",\"branch\":\"master\",\"opbuild.scripts\":\"1.30.7\",\"opbuild.htmltopdftool\":\"1.30.7\",\"opbuild.gitcontributorinformationresolver\":\"1.30.7\",\"opbuild_service\":\"1.30.130.0\",\"docfx.console\":\"2.15.4\",\"opbuild.resolvedependencyconsole\":\"1.30.7\",\"opbuild.schemavalidationconsole\":\"1.30.7\",\"opbuild.redirectionresolver\":\"1.30.7\",\"opbuild.templates.intellisense\":\"1.30.7\",\"dependencies\":[{\"branch\":\"preview\",\"path\":\"_themes\",\"url\":\"https://github.com/Microsoft/templates.docs.msft\",\"commit_id\":\"0df323bd2f29f4492cdffcf9fc99d76a426b2407\",\"opbuild.templates.common\":\"1.30.7\"},{\"branch\":\"master\",\"path\":\"_themes.pdf\",\"url\":\"https://github.com/Microsoft/templates.docs.msft.pdf\",\"commit_id\":\"ed2aa9642124365e156c2670dab210e368095ebd\",\"opbuild.templates.common\":\"1.30.7\"}]}"}