{"author":"dotnet-bot","ms.author":"dotnetcontent","manager":"wpickett","breadcrumb_path":"/dotnet-internal/toc.json","ms.topic":"managed-reference","ms.prod":".net","search.ms_sitename":"Docs","search.ms_docsetname":"docs-internal","version":0,"locale":"en-us","site_name":"Docs","search.ms_product":"MSDN","depot_name":"MSDN.docs-internal","original_ref_skeleton_git_url":"https://github.com/dotnet/docs-internal/blob/master/api/System.Net.WebHeaderCollection.yml","open_to_public_contributors":false,"api_name":["System.Net.WebHeaderCollection","System.Net.WebHeaderCollection..ctor","System.Net.WebHeaderCollection.Add","System.Net.WebHeaderCollection.AddWithoutValidate","System.Net.WebHeaderCollection.AllKeys","System.Net.WebHeaderCollection.Clear","System.Net.WebHeaderCollection.Count","System.Net.WebHeaderCollection.Get","System.Net.WebHeaderCollection.GetEnumerator","System.Net.WebHeaderCollection.GetKey","System.Net.WebHeaderCollection.GetObjectData","System.Net.WebHeaderCollection.GetValues","System.Net.WebHeaderCollection.IsRestricted","System.Net.WebHeaderCollection.Item","System.Net.WebHeaderCollection.Keys","System.Net.WebHeaderCollection.OnDeserialization","System.Net.WebHeaderCollection.Remove","System.Net.WebHeaderCollection.Set","System.Net.WebHeaderCollection.ISerializable.GetObjectData","System.Net.WebHeaderCollection.ToByteArray","System.Net.WebHeaderCollection.ToString"],"api_location":["System.dll"],"topic_type":["apiref"],"api_type":["Assembly"],"f1_keywords":["System.Net.WebHeaderCollection","System::Net::WebHeaderCollection","System.Net.WebHeaderCollection.#ctor","System::Net::WebHeaderCollection::#ctor","System.Net.WebHeaderCollection.Add","System::Net::WebHeaderCollection::Add","System.Net.WebHeaderCollection.AddWithoutValidate","System::Net::WebHeaderCollection::AddWithoutValidate","System.Net.WebHeaderCollection.AllKeys","System::Net::WebHeaderCollection::AllKeys","System.Net.WebHeaderCollection.Clear","System::Net::WebHeaderCollection::Clear","System.Net.WebHeaderCollection.Count","System::Net::WebHeaderCollection::Count","System.Net.WebHeaderCollection.Get","System::Net::WebHeaderCollection::Get","System.Net.WebHeaderCollection.GetEnumerator","System::Net::WebHeaderCollection::GetEnumerator","System.Net.WebHeaderCollection.GetKey","System::Net::WebHeaderCollection::GetKey","System.Net.WebHeaderCollection.GetObjectData","System::Net::WebHeaderCollection::GetObjectData","System.Net.WebHeaderCollection.GetValues","System::Net::WebHeaderCollection::GetValues","System.Net.WebHeaderCollection.IsRestricted","System::Net::WebHeaderCollection::IsRestricted","System.Net.WebHeaderCollection.Item","System::Net::WebHeaderCollection::Item","System.Net.WebHeaderCollection.Keys","System::Net::WebHeaderCollection::Keys","System.Net.WebHeaderCollection.OnDeserialization","System::Net::WebHeaderCollection::OnDeserialization","System.Net.WebHeaderCollection.Remove","System::Net::WebHeaderCollection::Remove","System.Net.WebHeaderCollection.Set","System::Net::WebHeaderCollection::Set","System.Net.WebHeaderCollection.System#Runtime#Serialization#ISerializable#GetObjectData","System::Net::WebHeaderCollection::System#Runtime#Serialization#ISerializable#GetObjectData","System.Net.WebHeaderCollection.ToByteArray","System::Net::WebHeaderCollection::ToByteArray","System.Net.WebHeaderCollection.ToString","System::Net::WebHeaderCollection::ToString"],"dev_langs":["csharp"],"updated_at":"2017-03-23 06:04 AM","document_id":"97021eab-08fe-3bb6-386e-189df147abe1","content_git_url":"https://github.com/TianqiZhang/ECMA2YamlTestRepo2/blob/master/xml/System.Net/WebHeaderCollection.xml","layout":"Reference","pagetype":"Reference","title":"WebHeaderCollection class | Microsoft Docs","description":"Contains protocol headers associated with a request or response.\n","toc_asset_id":"api/_splitted/System.Net/toc.json","toc_rel":"_splitted/System.Net/toc.json","source_url":"","ms.assetid":"System.Net.WebHeaderCollection","canonical_url":"https://ppe.docs.microsoft.com/en-us/dotnet/api/system.net.webheadercollection","is_dynamic_rendering":true,"content_type":"application/json","publish_version":"{\"opbuild.templates.docs\":\"1.29.2\",\"commit_id\":\"4daaa1618c43f8b649d421fc60ed8e3aaba1cba7\",\"branch\":\"master\",\"opbuild.scripts\":\"1.29.2\",\"opbuild.htmltopdftool\":\"1.29.2\",\"opbuild.gitcontributorinformationresolver\":\"1.29.2\",\"opbuild_service\":\"1.29.123.0\",\"docfx.console\":\"2.14.1\",\"opbuild.resolvedependencyconsole\":\"1.29.2\",\"opbuild.schemavalidationconsole\":\"1.29.2\",\"opbuild.redirectionresolver\":\"1.29.2\",\"opbuild.templates.intellisense\":\"1.29.2\",\"dependencies\":[{\"branch\":\"preview\",\"path\":\"_themes\",\"url\":\"https://github.com/Microsoft/templates.docs.msft\",\"commit_id\":\"eff7969f07a808864b2febe5a48618a2674e22af\",\"opbuild.templates.common\":\"1.29.2\"},{\"branch\":\"master\",\"path\":\"_themes.pdf\",\"url\":\"https://github.com/Microsoft/templates.docs.msft.pdf\",\"commit_id\":\"b2158fbf2c62f32aff19e6f61397f4caa40b05f7\",\"opbuild.templates.common\":\"1.29.2\"}]}"}