{"author":"dotnet-bot","ms.author":"dotnetcontent","manager":"wpickett","breadcrumb_path":"/dotnet/toc.json","apiPlatform":"dotnet","ms.topic":"managed-reference","ms.prod":".net","search.ms_sitename":"Docs","search.ms_docsetname":"docs-internal","version":0,"locale":"en-us","site_name":"Docs","search.ms_product":"MSDN","depot_name":"MSDN.docs-internal","original_ref_skeleton_git_url":"https://github.com/dotnet/docs-internal/blob/master/api/System.Activities.Presentation.PropertyEditing.PropertyValue.yml","open_to_public_contributors":false,"api_name":["System.Activities.Presentation.PropertyEditing.PropertyValue","System.Activities.Presentation.PropertyEditing.PropertyValue..ctor","System.Activities.Presentation.PropertyEditing.PropertyValue.CanConvertFromString","System.Activities.Presentation.PropertyEditing.PropertyValue.CatchExceptions","System.Activities.Presentation.PropertyEditing.PropertyValue.ClearValue","System.Activities.Presentation.PropertyEditing.PropertyValue.Collection","System.Activities.Presentation.PropertyEditing.PropertyValue.ConvertStringToValue","System.Activities.Presentation.PropertyEditing.PropertyValue.ConvertValueToString","System.Activities.Presentation.PropertyEditing.PropertyValue.GetValueCore","System.Activities.Presentation.PropertyEditing.PropertyValue.HasSubProperties","System.Activities.Presentation.PropertyEditing.PropertyValue.IsCollection","System.Activities.Presentation.PropertyEditing.PropertyValue.IsDefaultValue","System.Activities.Presentation.PropertyEditing.PropertyValue.IsMixedValue","System.Activities.Presentation.PropertyEditing.PropertyValue.NotifyRootValueChanged","System.Activities.Presentation.PropertyEditing.PropertyValue.NotifySubPropertyChanged","System.Activities.Presentation.PropertyEditing.PropertyValue.OnPropertyChanged","System.Activities.Presentation.PropertyEditing.PropertyValue.OnPropertyValueException","System.Activities.Presentation.PropertyEditing.PropertyValue.ParentProperty","System.Activities.Presentation.PropertyEditing.PropertyValue.PropertyChanged","System.Activities.Presentation.PropertyEditing.PropertyValue.add_PropertyChanged","System.Activities.Presentation.PropertyEditing.PropertyValue.remove_PropertyChanged","System.Activities.Presentation.PropertyEditing.PropertyValue.PropertyValueException","System.Activities.Presentation.PropertyEditing.PropertyValue.add_PropertyValueException","System.Activities.Presentation.PropertyEditing.PropertyValue.remove_PropertyValueException","System.Activities.Presentation.PropertyEditing.PropertyValue.RootValueChanged","System.Activities.Presentation.PropertyEditing.PropertyValue.add_RootValueChanged","System.Activities.Presentation.PropertyEditing.PropertyValue.remove_RootValueChanged","System.Activities.Presentation.PropertyEditing.PropertyValue.SetValueCore","System.Activities.Presentation.PropertyEditing.PropertyValue.Source","System.Activities.Presentation.PropertyEditing.PropertyValue.StringValue","System.Activities.Presentation.PropertyEditing.PropertyValue.SubProperties","System.Activities.Presentation.PropertyEditing.PropertyValue.SubPropertyChanged","System.Activities.Presentation.PropertyEditing.PropertyValue.add_SubPropertyChanged","System.Activities.Presentation.PropertyEditing.PropertyValue.remove_SubPropertyChanged","System.Activities.Presentation.PropertyEditing.PropertyValue.ValidateValue","System.Activities.Presentation.PropertyEditing.PropertyValue.Value"],"api_location":["System.Activities.Presentation.dll"],"topic_type":["apiref"],"api_type":["Assembly"],"f1_keywords":["System.Activities.Presentation.PropertyEditing.PropertyValue","System::Activities::Presentation::PropertyEditing::PropertyValue","System.Activities.Presentation.PropertyEditing.PropertyValue.#ctor","System::Activities::Presentation::PropertyEditing::PropertyValue::#ctor","System.Activities.Presentation.PropertyEditing.PropertyValue.CanConvertFromString","System::Activities::Presentation::PropertyEditing::PropertyValue::CanConvertFromString","System.Activities.Presentation.PropertyEditing.PropertyValue.CatchExceptions","System::Activities::Presentation::PropertyEditing::PropertyValue::CatchExceptions","System.Activities.Presentation.PropertyEditing.PropertyValue.ClearValue","System::Activities::Presentation::PropertyEditing::PropertyValue::ClearValue","System.Activities.Presentation.PropertyEditing.PropertyValue.Collection","System::Activities::Presentation::PropertyEditing::PropertyValue::Collection","System.Activities.Presentation.PropertyEditing.PropertyValue.ConvertStringToValue","System::Activities::Presentation::PropertyEditing::PropertyValue::ConvertStringToValue","System.Activities.Presentation.PropertyEditing.PropertyValue.ConvertValueToString","System::Activities::Presentation::PropertyEditing::PropertyValue::ConvertValueToString","System.Activities.Presentation.PropertyEditing.PropertyValue.GetValueCore","System::Activities::Presentation::PropertyEditing::PropertyValue::GetValueCore","System.Activities.Presentation.PropertyEditing.PropertyValue.HasSubProperties","System::Activities::Presentation::PropertyEditing::PropertyValue::HasSubProperties","System.Activities.Presentation.PropertyEditing.PropertyValue.IsCollection","System::Activities::Presentation::PropertyEditing::PropertyValue::IsCollection","System.Activities.Presentation.PropertyEditing.PropertyValue.IsDefaultValue","System::Activities::Presentation::PropertyEditing::PropertyValue::IsDefaultValue","System.Activities.Presentation.PropertyEditing.PropertyValue.IsMixedValue","System::Activities::Presentation::PropertyEditing::PropertyValue::IsMixedValue","System.Activities.Presentation.PropertyEditing.PropertyValue.NotifyRootValueChanged","System::Activities::Presentation::PropertyEditing::PropertyValue::NotifyRootValueChanged","System.Activities.Presentation.PropertyEditing.PropertyValue.NotifySubPropertyChanged","System::Activities::Presentation::PropertyEditing::PropertyValue::NotifySubPropertyChanged","System.Activities.Presentation.PropertyEditing.PropertyValue.OnPropertyChanged","System::Activities::Presentation::PropertyEditing::PropertyValue::OnPropertyChanged","System.Activities.Presentation.PropertyEditing.PropertyValue.OnPropertyValueException","System::Activities::Presentation::PropertyEditing::PropertyValue::OnPropertyValueException","System.Activities.Presentation.PropertyEditing.PropertyValue.ParentProperty","System::Activities::Presentation::PropertyEditing::PropertyValue::ParentProperty","System.Activities.Presentation.PropertyEditing.PropertyValue.PropertyChanged","System::Activities::Presentation::PropertyEditing::PropertyValue::PropertyChanged","System.Activities.Presentation.PropertyEditing.PropertyValue.PropertyValueException","System::Activities::Presentation::PropertyEditing::PropertyValue::PropertyValueException","System.Activities.Presentation.PropertyEditing.PropertyValue.RootValueChanged","System::Activities::Presentation::PropertyEditing::PropertyValue::RootValueChanged","System.Activities.Presentation.PropertyEditing.PropertyValue.SetValueCore","System::Activities::Presentation::PropertyEditing::PropertyValue::SetValueCore","System.Activities.Presentation.PropertyEditing.PropertyValue.Source","System::Activities::Presentation::PropertyEditing::PropertyValue::Source","System.Activities.Presentation.PropertyEditing.PropertyValue.StringValue","System::Activities::Presentation::PropertyEditing::PropertyValue::StringValue","System.Activities.Presentation.PropertyEditing.PropertyValue.SubProperties","System::Activities::Presentation::PropertyEditing::PropertyValue::SubProperties","System.Activities.Presentation.PropertyEditing.PropertyValue.SubPropertyChanged","System::Activities::Presentation::PropertyEditing::PropertyValue::SubPropertyChanged","System.Activities.Presentation.PropertyEditing.PropertyValue.ValidateValue","System::Activities::Presentation::PropertyEditing::PropertyValue::ValidateValue","System.Activities.Presentation.PropertyEditing.PropertyValue.Value","System::Activities::Presentation::PropertyEditing::PropertyValue::Value"],"dev_langs":["csharp"],"updated_at":"2017-03-31 05:47 AM","document_id":"3c691f2d-8668-d12d-8b44-58d66f9bbf50","content_git_url":"https://github.com/dotnet/docs-internal/blob/master/xml/System.Activities.Presentation.PropertyEditing/PropertyValue.xml","layout":"Reference","pagetype":"Reference","title":"PropertyValue class | Microsoft Docs","description":"Maintains a data model for the value of a property in the property grid.\n","toc_asset_id":"api/_splitted/System.Activities.Presentation.PropertyEditing/toc.json","toc_rel":"_splitted/System.Activities.Presentation.PropertyEditing/toc.json","source_url":"","ms.assetid":"System.Activities.Presentation.PropertyEditing.PropertyValue","canonical_url":"https://ppe.docs.microsoft.com/en-us/dotnet/api/system.activities.presentation.propertyediting.propertyvalue","is_dynamic_rendering":true,"content_type":"application/json","publish_version":"{\"opbuild.templates.docs\":\"1.30.5\",\"commit_id\":\"43f5ba789f189193b4c4d74e0a16260c1101454d\",\"branch\":\"master\",\"opbuild.scripts\":\"1.30.5\",\"opbuild.htmltopdftool\":\"1.30.5\",\"opbuild.gitcontributorinformationresolver\":\"1.30.5\",\"opbuild_service\":\"1.30.130.0\",\"docfx.console\":\"2.15.3\",\"opbuild.resolvedependencyconsole\":\"1.30.5\",\"opbuild.schemavalidationconsole\":\"1.30.5\",\"opbuild.redirectionresolver\":\"1.30.5\",\"opbuild.templates.intellisense\":\"1.30.5\",\"dependencies\":[{\"branch\":\"preview\",\"path\":\"_themes\",\"url\":\"https://github.com/Microsoft/templates.docs.msft\",\"commit_id\":\"54663af12f6666aa880e36ab751eba06506811b1\",\"opbuild.templates.common\":\"1.30.5\"},{\"branch\":\"master\",\"path\":\"_themes.pdf\",\"url\":\"https://github.com/Microsoft/templates.docs.msft.pdf\",\"commit_id\":\"ed2aa9642124365e156c2670dab210e368095ebd\",\"opbuild.templates.common\":\"1.30.5\"}]}"}