[{"toc_title":"System.Xml.Serialization.Configuration","href":"../../system.xml.serialization.configuration","children":[{"toc_title":"DateTimeSerializationSection","href":"../../system.xml.serialization.configuration.datetimeserializationsection","version":["netframework-3.0","netframework-3.5-client","netframework-3.5","netframework-4.0-client","netframework-4.0","netframework-4.5.1","netframework-4.5.2","netframework-4.5","netframework-4.6.1","netframework-4.6.2","netframework-4.6"]},{"toc_title":"DateTimeSerializationSection.DateTimeSerializationMode","href":"../../system.xml.serialization.configuration.datetimeserializationsection.datetimeserializationmode","version":["netframework-3.0","netframework-3.5-client","netframework-3.5","netframework-4.0-client","netframework-4.0","netframework-4.5.1","netframework-4.5.2","netframework-4.5","netframework-4.6.1","netframework-4.6.2","netframework-4.6"]},{"toc_title":"RootedPathValidator","href":"../../system.xml.serialization.configuration.rootedpathvalidator","version":["netframework-3.0","netframework-3.5-client","netframework-3.5","netframework-4.0-client","netframework-4.0","netframework-4.5.1","netframework-4.5.2","netframework-4.5","netframework-4.6.1","netframework-4.6.2","netframework-4.6"]},{"toc_title":"SchemaImporterExtensionElement","href":"../../system.xml.serialization.configuration.schemaimporterextensionelement","version":["netframework-3.0","netframework-3.5-client","netframework-3.5","netframework-4.0-client","netframework-4.0","netframework-4.5.1","netframework-4.5.2","netframework-4.5","netframework-4.6.1","netframework-4.6.2","netframework-4.6"]},{"toc_title":"SchemaImporterExtensionElementCollection","href":"../../system.xml.serialization.configuration.schemaimporterextensionelementcollection","version":["netframework-3.0","netframework-3.5-client","netframework-3.5","netframework-4.0-client","netframework-4.0","netframework-4.5.1","netframework-4.5.2","netframework-4.5","netframework-4.6.1","netframework-4.6.2","netframework-4.6"]},{"toc_title":"SchemaImporterExtensionsSection","href":"../../system.xml.serialization.configuration.schemaimporterextensionssection","version":["netframework-3.0","netframework-3.5-client","netframework-3.5","netframework-4.0-client","netframework-4.0","netframework-4.5.1","netframework-4.5.2","netframework-4.5","netframework-4.6.1","netframework-4.6.2","netframework-4.6"]},{"toc_title":"SerializationSectionGroup","href":"../../system.xml.serialization.configuration.serializationsectiongroup","version":["netframework-3.0","netframework-3.5-client","netframework-3.5","netframework-4.0-client","netframework-4.0","netframework-4.5.1","netframework-4.5.2","netframework-4.5","netframework-4.6.1","netframework-4.6.2","netframework-4.6"]},{"toc_title":"XmlSerializerSection","href":"../../system.xml.serialization.configuration.xmlserializersection","version":["netframework-3.0","netframework-3.5-client","netframework-3.5","netframework-4.0-client","netframework-4.0","netframework-4.5.1","netframework-4.5.2","netframework-4.5","netframework-4.6.1","netframework-4.6.2","netframework-4.6"]}],"version":["netframework-3.0","netframework-3.5-client","netframework-3.5","netframework-4.0-client","netframework-4.0","netframework-4.5.1","netframework-4.5.2","netframework-4.5","netframework-4.6.1","netframework-4.6.2","netframework-4.6"],"pdf_name":"/api/_splitted/System.Xml.Serialization.Configuration.pdf"}]